AUTHORS
LICENCE
MANIFEST.in
README.md
setup.py
django_simple_website_meta.egg-info/PKG-INFO
django_simple_website_meta.egg-info/SOURCES.txt
django_simple_website_meta.egg-info/dependency_links.txt
django_simple_website_meta.egg-info/not-zip-safe
django_simple_website_meta.egg-info/requires.txt
django_simple_website_meta.egg-info/top_level.txt
simplewebsitemeta/__init__.py
simplewebsitemeta/models.py
simplewebsitemeta/migrations/0001_initial.py
simplewebsitemeta/migrations/__init__.py