Metadata-Version: 1.0
Name: django-simple-website-meta
Version: 0.0.1
Summary: Fetch basic meta data for URLS in Django
Home-page: https://github.com/joncombe/django-simple-website-meta
Author: Jon Combe
Author-email: pypi@joncombe.net
License: BSD licence, see LICENCE file
Platform: UNKNOWN
